efb_mp_instantview_middleware/__init__.py
efb_mp_instantview_middleware/__version__.py
efb_mp_instantview_middleware/telegraph.py
efb_mp_instantview_middleware-0.3.2.dist-info/METADATA
efb_mp_instantview_middleware-0.3.2.dist-info/WHEEL
efb_mp_instantview_middleware-0.3.2.dist-info/entry_points.txt
efb_mp_instantview_middleware-0.3.2.dist-info/top_level.txt
efb_mp_instantview_middleware-0.3.2.dist-info/RECORD
