Metadata-Version: 2.1
Name: efb-mp-instantview-middleware
Version: 0.3.2
Summary: WeChat Middleware of EH Forwarder Bot to enable instant        view for official accounts' articles
Home-page: https://github.com/catbaron0/efb-mp-instant-middleware
Author: catbaron
Author-email: catbaron@live.cn
License: AGPLv3+
Keywords: ehforwarderbot,EH Forwarder Bot,EH Forwarder Bot Slave Channel,wechat,weixin,chatbot
Platform: UNKNOWN
Classifier: Development Status :: 5 - Production/Stable
Classifier: License :: OSI Approved :: GNU Affero General Public License v3 or later (AGPLv3+)
Classifier: Intended Audience :: Developers
Classifier: Intended Audience :: End Users/Desktop
Classifier: Programming Language :: Python :: 3 :: Only
Classifier: Programming Language :: Python :: 3.6
Classifier: Programming Language :: Python :: 3.7
Classifier: Topic :: Communications :: Chat
Classifier: Topic :: Utilities
Requires-Python: >=3.6
Requires-Dist: ehforwarderbot (>=2.0.0)
Requires-Dist: PyYaml
Requires-Dist: bs4
Requires-Dist: requests[socks]
